{
  "$schema": "https://raw.githubusercontent.com/NethermindEth/core-scripts/refs/heads/main/schemas/config.json",
  "Init": {
    "ChainSpecPath": "chainspec/arbitrum-sepolia.json",
    "BaseDbPath": "nethermind_db/arbitrum-sepolia-archive",
    "LogFileName": "arbitrum-sepolia-archive.log"
  },
  "TxPool": {
    "BlobsSupport": "Disabled"
  },
  "Discovery": {
    "DiscoveryVersion": "V5"
  },
  "JsonRpc": {
    "Enabled": true,
    "Port": 20545,
    "EnginePort": 20551,
    "UnsecureDevNoRpcAuthentication": true,
    "AdditionalRpcUrls": [
      "http://0.0.0.0:28551|http;ws|net;eth;subscribe;web3;client;debug"
    ],
    "EnabledModules": [
      "Admin",
      "Clique",
      "Consensus",
      "Db",
      "Debug",
      "Deposit",
      "Erc20",
      "Eth",
      "Evm",
      "Net",
      "Nft",
      "Parity",
      "Personal",
      "Proof",
      "Subscribe",
      "Trace",
      "TxPool",
      "Vault",
      "Web3",
      "Arbitrum"
    ]
  },
  "Pruning": {
    "Mode": "None"
  },
  "Blocks": {
    "PreWarmStateOnBlockProcessing": false
  },
  "Metrics": {
    "NodeName": "Nethermind Arbitrum Sepolia Archive"
  },
  "Merge": {
    "Enabled": true
  }
}
